log_sculptor/__init__.py
log_sculptor/cli.py
log_sculptor/di.py
log_sculptor/exceptions.py
log_sculptor/core/__init__.py
log_sculptor/core/clustering.py
log_sculptor/core/drift.py
log_sculptor/core/merging.py
log_sculptor/core/models.py
log_sculptor/core/naming.py
log_sculptor/core/patterns.py
log_sculptor/core/streaming.py
log_sculptor/core/tokenizer.py
log_sculptor/outputs/__init__.py
log_sculptor/outputs/duckdb.py
log_sculptor/outputs/jsonl.py
log_sculptor/outputs/parquet.py
log_sculptor/outputs/sqlite.py
log_sculptor/parsers/__init__.py
log_sculptor/parsers/multiline.py
log_sculptor/testing/__init__.py
log_sculptor/testing/fixtures.py
log_sculptor/testing/generators.py
log_sculptor/testing/mocks.py
log_sculptor/types/__init__.py
log_sculptor/types/detector.py
log_sculptor/types/timestamp.py
log_sculptor-0.1.0.dist-info/METADATA
log_sculptor-0.1.0.dist-info/WHEEL
log_sculptor-0.1.0.dist-info/entry_points.txt
log_sculptor-0.1.0.dist-info/RECORD
