Metadata-Version: 2.4
Name: log-sculptor
Version: 0.1.0
Summary: Parse unstructured logs by learning patterns automatically
Project-URL: Homepage, https://github.com/kmcallorum/log-sculptor
Project-URL: Repository, https://github.com/kmcallorum/log-sculptor
Project-URL: Issues, https://github.com/kmcallorum/log-sculptor/issues
Author: Kevin McAllorum
License-Expression: MIT
Keywords: cli,data-pipeline,etl,log-analysis,logging,parsing,patterns
Classifier: Development Status :: 3 - Alpha
Classifier: Environment :: Console
Classifier: Intended Audience :: Developers
Classifier: Intended Audience :: System Administrators
Classifier: License :: OSI Approved :: MIT License
Classifier: Programming Language :: Python :: 3
Classifier: Programming Language :: Python :: 3.10
Classifier: Programming Language :: Python :: 3.11
Classifier: Programming Language :: Python :: 3.12
Classifier: Topic :: System :: Logging
Classifier: Topic :: Text Processing
Requires-Python: >=3.10
Requires-Dist: click>=8.0
Requires-Dist: orjson>=3.9
Requires-Dist: python-dateutil>=2.8
Requires-Dist: regex>=2023.0
Provides-Extra: all
Requires-Dist: duckdb>=0.9; extra == 'all'
Requires-Dist: pyarrow>=14.0; extra == 'all'
Provides-Extra: dev
Requires-Dist: pytest-agents>=1.0.9; (python_version >= '3.11') and extra == 'dev'
Requires-Dist: pytest-cov>=4.0; extra == 'dev'
Requires-Dist: pytest>=7.0; extra == 'dev'
Requires-Dist: ruff>=0.1.0; extra == 'dev'
Provides-Extra: duckdb
Requires-Dist: duckdb>=0.9; extra == 'duckdb'
Provides-Extra: parquet
Requires-Dist: pyarrow>=14.0; extra == 'parquet'
